setup.py
siggy/__init__.py
siggy/siggy.py
siggy/version.py
siggy.egg-info/PKG-INFO
siggy.egg-info/SOURCES.txt
siggy.egg-info/dependency_links.txt
siggy.egg-info/requires.txt
siggy.egg-info/top_level.txt