Metadata-Version: 1.0
Name: siggy
Version: 0.1.0
Summary: A little module for verifying bitcoin signatures
Home-page: https://github.com/wiggzz/siggy
Author: Will James
Author-email: jameswt@gmail.com
License: MIT
Platform: UNKNOWN
